dnn/__init__.py
dnn/dataset.py
dnn/datautil.py
dnn/dnn.py
dnn/frozen_graph.py
dnn/grid_search.py
dnn/label.py
dnn/layers.py
dnn/metrics.py
dnn/multidnn.py
dnn/normalizer.py
dnn/optimizers.py
dnn/overfit.py
dnn/plot.py
dnn/predutil.py
dnn/priors.py
dnn/quant.py
dnn/result.py
dnn/saved_model.py
dnn/split.py
dnn/tflite.py
dnn/callbacks/__init__.py
dnn/callbacks/base.py
dnn/callbacks/best_metrics.py
dnn/callbacks/clear_output.py
dnn/callbacks/confusion_matrix.py
dnn/callbacks/numpy_metric.py
dnn/callbacks/plot_progress.py
dnn/costs/__init__.py
dnn/costs/association.py
dnn/costs/costs.py
dnn/costs/focal_loss.py
dnn/costs/gan.py
dnn/custlayers/fixed_batchnorm.py
dnn/custlayers/roipool.py
dnn/export/skitai/__export__.py
dnn/export/skitai/__init__.py
dnn/losses/__init__.py
dnn/losses/focal_losses.py
dnn/losses/rpn.py
dnn/losses/ssd.py
dnn/metrics/__init__.py
dnn/metrics/mAP.py
dnn/metrics/skipping.py
dnn/problems/od/__init__.py
dnn/problems/od/anbox.py
dnn/problems/od/resnet.py
dnn/problems/od/rpn.py
dnn/problems/segmentation/__init__.py
dnn/problems/segmentation/metrics.py
dnn/problems/segmentation/unet.py
dnn/problems/similarity/selectors.py
dnn/problems/similarity/tfidf.py
dnn/processing/audio/augment.py
dnn/processing/audio/augments.py
dnn/processing/audio/feature.py
dnn/processing/audio/jcompat.py
dnn/processing/audio/noise_composer.py
dnn/processing/audio/silence_detection.py
dnn/processing/audio/sources.py
dnn/processing/audio/spectrograms.py
dnn/processing/audio/utils.py
dnn/processing/audio/vad.py
dnn/processing/audio/noise_waves/README.md
dnn/processing/image/augment.py
dnn/processing/image/camera_griding.py
dnn/processing/image/cutter.py
dnn/processing/image/face.py
dnn/processing/image/facenet.py
dnn/processing/image/img_util.py
dnn/processing/image/measure.py
dnn/processing/image/rect_util.py
dnn/processing/image/transform.py
dnn/processing/image/facenet/README.md
dnn/processing/image/mtcnn/__init__.py
dnn/processing/image/mtcnn/layer_factory.py
dnn-0.7.5.dist-info/LICENSE
dnn-0.7.5.dist-info/METADATA
dnn-0.7.5.dist-info/WHEEL
dnn-0.7.5.dist-info/top_level.txt
dnn-0.7.5.dist-info/RECORD
