Metadata-Version: 2.1
Name: dnn
Version: 0.7.5
Summary: Machine Learning Utilities
Home-page: https://gitlab.com/tfserver/dnn
Author: Hans Roh
Author-email: hansroh@gmail.com
License: MIT
Download-URL: https://pypi.python.org/pypi/dnn
Platform: posix
Classifier: License :: OSI Approved :: MIT License
Classifier: Development Status :: 1 - Planning
Classifier: Environment :: Console
Classifier: Topic :: Software Development :: Libraries :: Python Modules
Classifier: Topic :: Scientific/Engineering :: Artificial Intelligence
Classifier: Intended Audience :: Developers
Classifier: Intended Audience :: Science/Research
Classifier: Programming Language :: Python
Classifier: Programming Language :: Python :: 3
License-File: LICENSE
Requires-Dist: rs4
Requires-Dist: tfserver
Requires-Dist: numpy
Requires-Dist: scikit-learn
Requires-Dist: future
Requires-Dist: networkx
Requires-Dist: hyperopt
Requires-Dist: protobuf (>=3.20)
Requires-Dist: dill
Requires-Dist: webrtcvad
Requires-Dist: exif
Requires-Dist: fdet
